{
	"id": "5897e27e-eed6-41c2-bf84-bd01be92a3ee",
	"name": "TT freeda_it",
	"values": [
		{
			"key": "client_key",
			"value": "awusuriz4udhfisu",
			"enabled": true
		},
		{
			"key": "client_secret",
			"value": "575232115b56cd05efe56212eedba829",
			"enabled": true
		},
		{
			"key": "code",
			"value": "xMVfmYNgNMHLUmugceuDW0sAgfih4y36Av3jabNo50BZT_RhwoAsJmsVpyjfdFyBenDHS0ldXDn7jm8QftrGOoGLWb9Q7WLWIojbvXkayJc%2A3%215245",
			"enabled": true
		},
		{
			"key": "scope",
			"value": "user.info.basic,video.list",
			"enabled": true
		},
		{
			"key": "redirect_uri",
			"value": "www.freedamedia.com",
			"enabled": true
		},
		{
			"key": "state",
			"value": "gcq1w5tkyy6",
			"enabled": true
		},
		{
			"key": "token",
			"value": "act.ee71d0083e49d3347f5fad699d889c74U7R6tNCMLbWmyc8Kxelc8JZH0HbS!5191",
			"enabled": true
		},
		{
			"key": "refresh_token",
			"value": "rft.3fc10e3eb4878baab0255aad0cbe953755CrBHmyEsla0hCvT4DKN0A4Iorq!5249",
			"enabled": true
		}
	],
	"_postman_variable_scope": "environment",
	"_postman_exported_at": "2022-11-11T13:13:09.695Z",
	"_postman_exported_using": "Postman/8.5.1"
}